tabsdata_salesforce-1.5.0.data/purelib/tabsdata_salesforce/__init__.py
tabsdata_salesforce-1.5.0.data/purelib/tabsdata_salesforce/_connector.py
tabsdata_salesforce-1.5.0.data/purelib/tabsdata_salesforce/assets/manifest/BANNER
tabsdata_salesforce-1.5.0.data/purelib/tabsdata_salesforce/assets/manifest/LICENSE
tabsdata_salesforce-1.5.0.data/purelib/tabsdata_salesforce/assets/manifest/README-PyPi.md
tabsdata_salesforce-1.5.0.data/purelib/tabsdata_salesforce/assets/manifest/RELEASE-NOTES
tabsdata_salesforce-1.5.0.data/purelib/tabsdata_salesforce/assets/manifest/SOURCETRACK.yaml
tabsdata_salesforce-1.5.0.data/purelib/tabsdata_salesforce/assets/manifest/THIRD-PARTY
tabsdata_salesforce-1.5.0.data/purelib/tabsdata_salesforce/assets/manifest/VERSION
tabsdata_salesforce-1.5.0.dist-info/licenses/tabsdata_salesforce/assets/manifest/LICENSE
tabsdata_salesforce-1.5.0.dist-info/METADATA
tabsdata_salesforce-1.5.0.dist-info/WHEEL
tabsdata_salesforce-1.5.0.dist-info/top_level.txt
tabsdata_salesforce-1.5.0.dist-info/RECORD
